wolfpydike/DLBreach_Modules.py
wolfpydike/PointsCoordinates.py
wolfpydike/__init__.py
wolfpydike/_add_path.py
wolfpydike/compute_Qout.py
wolfpydike/dikeBreaching.py
wolfpydike-0.1.5.dist-info/METADATA
wolfpydike-0.1.5.dist-info/WHEEL
wolfpydike-0.1.5.dist-info/top_level.txt
wolfpydike-0.1.5.dist-info/RECORD
