Metadata-Version: 2.4
Name: wolfpydike
Version: 0.1.5
Summary: Dike breaching
Author-email: Vincent Schmitz <v.schmitz@uliege.be>, Pierre Archambeau <pierre.archambeau@uliege.be>
Project-URL: Homepage, https://uee.uliege.be/hece
Project-URL: Issues, https://uee.uliege.be/hece
Requires-Dist: numpy
Requires-Dist: matplotlib
Requires-Dist: scipy
